azure/__init__.py
azure/cli/__init__.py
azure/cli/command_modules/__init__.py
azure/cli/command_modules/security/__init__.py
azure/cli/command_modules/security/_client_factory.py
azure/cli/command_modules/security/_help.py
azure/cli/command_modules/security/_params.py
azure/cli/command_modules/security/_validators.py
azure/cli/command_modules/security/commands.py
azure/cli/command_modules/security/custom.py
opal_azure_cli_security-0.1.4.dist-info/METADATA
opal_azure_cli_security-0.1.4.dist-info/WHEEL
opal_azure_cli_security-0.1.4.dist-info/top_level.txt
opal_azure_cli_security-0.1.4.dist-info/RECORD
